{
  "obsidian-citation-plugin:insert-markdown-citation": [
    {
      "modifiers": [
        "Mod",
        "Shift"
      ],
      "key": "C"
    }
  ],
  "editor:insert-callout": [
    {
      "modifiers": [
        "Alt",
        "Mod",
        "Shift"
      ],
      "key": "A"
    }
  ],
  "obsidian-tasks-plugin:toggle-done": [
    {
      "modifiers": [
        "Alt",
        "Mod",
        "Shift"
      ],
      "key": "D"
    }
  ],
  "obsidian-tasks-plugin:edit-task": [
    {
      "modifiers": [
        "Alt",
        "Mod",
        "Shift"
      ],
      "key": "T"
    }
  ],
  "global-search-and-replace:search-and-replace": [
    {
      "modifiers": [
        "Alt",
        "Mod",
        "Shift"
      ],
      "key": "G"
    }
  ],
  "obisidian-note-linker:open-note-linker": [
    {
      "modifiers": [
        "Alt",
        "Meta",
        "Shift"
      ],
      "key": "L"
    }
  ],
  "supsub:wrap-sub": [
    {
      "modifiers": [
        "Alt",
        "Mod",
        "Shift"
      ],
      "key": "U"
    }
  ],
  "supsub:wrap-sup": [
    {
      "modifiers": [
        "Alt",
        "Mod",
        "Shift"
      ],
      "key": "S"
    }
  ],
  "code-block-from-selection:1b45501e-21f8-432b-818d-65b4622c5823": [
    {
      "modifiers": [
        "Alt",
        "Mod",
        "Shift"
      ],
      "key": "P"
    }
  ],
  "editor:fold-all": [
    {
      "modifiers": [
        "Alt",
        "Mod",
        "Shift"
      ],
      "key": "F"
    }
  ],
  "editor:unfold-all": [
    {
      "modifiers": [
        "Alt",
        "Ctrl",
        "Shift"
      ],
      "key": "F"
    }
  ],
  "code-block-from-selection:e3dea0f5-37f2-4d79-ae58-490af3228069": [
    {
      "modifiers": [
        "Alt",
        "Mod",
        "Shift"
      ],
      "key": "C"
    }
  ],
  "obsidian-toggle-case:toggle-case": [
    {
      "modifiers": [
        "Ctrl",
        "Shift"
      ],
      "key": "L"
    }
  ],
  "number-headings-obsidian:number-headings": [
    {
      "modifiers": [
        "Alt",
        "Mod",
        "Shift"
      ],
      "key": "H"
    }
  ]
}